commonuicomponents/__init__.py
commonuicomponents/animatedgif.py
commonuicomponents/appbuilder.py
commonuicomponents/applauncher.py
commonuicomponents/basetab.py
commonuicomponents/basetabloader.py
commonuicomponents/busymanager.py
commonuicomponents/periodicalafter.py
commonuicomponents/serialport.py
commonuicomponents/staticutils.py
commonuicomponents/version.py
commonuicomponents/json/__init__.py
commonuicomponents/json/config.py
commonuicomponents/json/json.py
commonuicomponents/json/storage.py
commonuicomponents/ports/__init__.py
commonuicomponents/ttk/__init__.py
commonuicomponents/ttk/commonuicomponents.py
commonuicomponents/ttk/multiplier.py
commonuicomponents/ttk/containers/__init__.py
commonuicomponents/ttk/containers/basecontainer.py
commonuicomponents/ttk/containers/container.py
commonuicomponents/ttk/containers/labeledcontainer.py
commonuicomponents/ttk/containers/labeledradiobuttongroup.py
commonuicomponents/ttk/containers/timepicker.py
commonuicomponents/ttk/containers/labeledwidget/__init__.py
commonuicomponents/ttk/containers/labeledwidget/basecontainer.py
commonuicomponents/ttk/containers/labeledwidget/container.py
commonuicomponents/ttk/containers/labeledwidget/labeledcontainer.py
commonuicomponents/ttk/widgets/__init__.py
commonuicomponents/ttk/widgets/checkbutton.py
commonuicomponents/ttk/widgets/combobox.py
commonuicomponents/ttk/widgets/entry.py
commonuicomponents/ttk/widgets/labeledscale.py
commonuicomponents/ttk/widgets/listbox.py
commonuicomponents/ttk/widgets/numberentry.py
commonuicomponents/ttk/widgets/scrollbar.py
commonuicomponents/ttk/widgets/smartwidget.py
commonuicomponents/ttk/widgets/spinbox.py
commonuicomponents/ttk/widgets/statefulbutton.py
common_ui_components-2.20.0.dist-info/LICENSE
common_ui_components-2.20.0.dist-info/METADATA
common_ui_components-2.20.0.dist-info/WHEEL
common_ui_components-2.20.0.dist-info/top_level.txt
common_ui_components-2.20.0.dist-info/RECORD
