Metadata-Version: 2.1
Name: common-ui-components
Version: 2.20.0
Summary: tkinter.ttk-based UI components
Home-page: https://github.com/RobinBobin/python3-common-ui-components
Author: Ruben Shalimov
Author-email: r_shalimov@inbox.ru
License: UNKNOWN
Platform: UNKNOWN
Classifier: Programming Language :: Python :: 3
Classifier: Operating System :: OS Independent
Requires-Dist: simple-common-utils
Requires-Dist: stringcase
